README.md
setup.py
monolithcaching/__init__.py
monolithcaching/errors.py
monolithcaching/register.py
monolithcaching/root_directory.py
monolithcaching/s3_worker.py
monolithcaching/version.py
monolithcaching/worker.py
monolithcaching.egg-info/PKG-INFO
monolithcaching.egg-info/SOURCES.txt
monolithcaching.egg-info/dependency_links.txt
monolithcaching.egg-info/entry_points.txt
monolithcaching.egg-info/requires.txt
monolithcaching.egg-info/top_level.txt
monolithcaching/cache/__init__.py
monolithcaching/console_commands/__init__.py
monolithcaching/console_commands/hello.py