Metadata-Version: 2.1
Name: monolithcaching
Version: 0.0.8
Summary: Python package for monolithcaching
Home-page: https://github.com/MonolithAILtd/caching
Author: Maxwell Flitton
Author-email: maxwell@monolithai.com
License: UNKNOWN
Platform: UNKNOWN
Classifier: Development Status :: 4 - Beta
Classifier: Programming Language :: Python :: 3
Classifier: Operating System :: OS Independent
Requires-Python: >=3
